ErfanIO
